{
  "frames": {
    "minotaur2_idle/COMPS.0000": {
      "frame": { "x": 106, "y": 10, "w": 103, "h": 92 },
      "rotated": false,
      "trimmed": true,
      "spriteSourceSize": { "x": 24, "y": 32, "w": 52, "h": 46 },
      "sourceSize": { "w": 100, "h": 100 },
      "pivot": { "x": 0.5, "y": 0.5 }
    },
    "minotaur2_idle/COMPS.0002": {
      "frame": { "x": 0, "y": 10, "w": 102, "h": 91 },
      "rotated": false,
      "trimmed": true,
      "spriteSourceSize": { "x": 25, "y": 32, "w": 51, "h": 45 },
      "sourceSize": { "w": 100, "h": 100 },
      "pivot": { "x": 0.5, "y": 0.5 }
    },
    "minotaur2_idle/COMPS.0004": {
      "frame": { "x": 533, "y": 10, "w": 102, "h": 93 },
      "rotated": false,
      "trimmed": true,
      "spriteSourceSize": { "x": 25, "y": 31, "w": 51, "h": 46 },
      "sourceSize": { "w": 100, "h": 100 },
      "pivot": { "x": 0.5, "y": 0.5 }
    },
    "minotaur2_idle/COMPS.0006": {
      "frame": { "x": 639, "y": 10, "w": 103, "h": 94 },
      "rotated": false,
      "trimmed": true,
      "spriteSourceSize": { "x": 25, "y": 31, "w": 52, "h": 47 },
      "sourceSize": { "w": 100, "h": 100 },
      "pivot": { "x": 0.5, "y": 0.5 }
    },
    "minotaur2_idle/COMPS.0008": {
      "frame": { "x": 958, "y": 10, "w": 102, "h": 96 },
      "rotated": false,
      "trimmed": true,
      "spriteSourceSize": { "x": 25, "y": 30, "w": 51, "h": 48 },
      "sourceSize": { "w": 100, "h": 100 },
      "pivot": { "x": 0.5, "y": 0.5 }
    },
    "minotaur2_idle/COMPS.0010": {
      "frame": { "x": 1169, "y": 10, "w": 102, "h": 98 },
      "rotated": false,
      "trimmed": true,
      "spriteSourceSize": { "x": 25, "y": 30, "w": 51, "h": 49 },
      "sourceSize": { "w": 100, "h": 100 },
      "pivot": { "x": 0.5, "y": 0.5 }
    },
    "minotaur2_idle/COMPS.0012": {
      "frame": { "x": 1275, "y": 10, "w": 101, "h": 99 },
      "rotated": false,
      "trimmed": true,
      "spriteSourceSize": { "x": 26, "y": 30, "w": 51, "h": 50 },
      "sourceSize": { "w": 100, "h": 100 },
      "pivot": { "x": 0.5, "y": 0.5 }
    },
    "minotaur2_idle/COMPS.0014": {
      "frame": { "x": 1484, "y": 10, "w": 99, "h": 100 },
      "rotated": false,
      "trimmed": true,
      "spriteSourceSize": { "x": 26, "y": 30, "w": 50, "h": 50 },
      "sourceSize": { "w": 100, "h": 100 },
      "pivot": { "x": 0.5, "y": 0.5 }
    },
    "minotaur2_idle/COMPS.0016": {
      "frame": { "x": 1690, "y": 10, "w": 99, "h": 101 },
      "rotated": false,
      "trimmed": true,
      "spriteSourceSize": { "x": 26, "y": 30, "w": 50, "h": 51 },
      "sourceSize": { "w": 100, "h": 100 },
      "pivot": { "x": 0.5, "y": 0.5 }
    },
    "minotaur2_idle/COMPS.0018": {
      "frame": { "x": 1587, "y": 10, "w": 99, "h": 100 },
      "rotated": false,
      "trimmed": true,
      "spriteSourceSize": { "x": 26, "y": 31, "w": 50, "h": 50 },
      "sourceSize": { "w": 100, "h": 100 },
      "pivot": { "x": 0.5, "y": 0.5 }
    },
    "minotaur2_idle/COMPS.0020": {
      "frame": { "x": 1380, "y": 10, "w": 100, "h": 99 },
      "rotated": false,
      "trimmed": true,
      "spriteSourceSize": { "x": 26, "y": 31, "w": 50, "h": 50 },
      "sourceSize": { "w": 100, "h": 100 },
      "pivot": { "x": 0.5, "y": 0.5 }
    },
    "minotaur2_idle/COMPS.0022": {
      "frame": { "x": 1064, "y": 10, "w": 101, "h": 97 },
      "rotated": false,
      "trimmed": true,
      "spriteSourceSize": { "x": 26, "y": 31, "w": 51, "h": 49 },
      "sourceSize": { "w": 100, "h": 100 },
      "pivot": { "x": 0.5, "y": 0.5 }
    },
    "minotaur2_idle/COMPS.0024": {
      "frame": { "x": 852, "y": 10, "w": 102, "h": 95 },
      "rotated": false,
      "trimmed": true,
      "spriteSourceSize": { "x": 25, "y": 31, "w": 51, "h": 48 },
      "sourceSize": { "w": 100, "h": 100 },
      "pivot": { "x": 0.5, "y": 0.5 }
    },
    "minotaur2_idle/COMPS.0026": {
      "frame": { "x": 746, "y": 10, "w": 102, "h": 94 },
      "rotated": false,
      "trimmed": true,
      "spriteSourceSize": { "x": 25, "y": 31, "w": 51, "h": 47 },
      "sourceSize": { "w": 100, "h": 100 },
      "pivot": { "x": 0.5, "y": 0.5 }
    },
    "minotaur2_idle/COMPS.0028": {
      "frame": { "x": 213, "y": 10, "w": 103, "h": 92 },
      "rotated": false,
      "trimmed": true,
      "spriteSourceSize": { "x": 25, "y": 31, "w": 52, "h": 46 },
      "sourceSize": { "w": 100, "h": 100 },
      "pivot": { "x": 0.5, "y": 0.5 }
    },
    "minotaur2_idle/COMPS.0030": {
      "frame": { "x": 320, "y": 10, "w": 102, "h": 92 },
      "rotated": false,
      "trimmed": true,
      "spriteSourceSize": { "x": 25, "y": 31, "w": 51, "h": 46 },
      "sourceSize": { "w": 100, "h": 100 },
      "pivot": { "x": 0.5, "y": 0.5 }
    }
  },
  "meta": {
    "app": "http://github.com/odrick/free-tex-packer-core",
    "version": "0.3.4",
    "image": "minotaur2_idle.webp",
    "format": "RGBA8888",
    "size": { "w": 2048, "h": 128 },
    "scale": 1
  }
}
